pcst_fast.pypy39-pp73-darwin.so
pcst_fast-1.0.10.dist-info/RECORD
pcst_fast-1.0.10.dist-info/WHEEL
pcst_fast-1.0.10.dist-info/top_level.txt
pcst_fast-1.0.10.dist-info/LICENSE.txt
pcst_fast-1.0.10.dist-info/METADATA
pcst_fast/test_pcst_fast.py
