Metadata-Version: 2.1
Name: pcst_fast
Version: 1.0.10
Summary: A fast implementation of the Goemans-Williamson scheme for the prize-collecting Steiner tree / forest problem.
Home-page: https://github.com/fraenkel-lab/pcst_fast
Author: ludwigschmidt
Author-email: alex@lenail.org
License: GNU General Public License
Requires-Python: >=3.8
License-File: LICENSE.txt
Requires-Dist: pybind11>=2.1.0
